runesanalyzer/__init__.py
runesanalyzer/data.py
runesanalyzer/reader.py
runesanalyzer/runes.py
runesanalyzer/scraper.py
runesanalyzer/sweden_runes.json
runesanalyzer/tests.py
runesanalyzer/utils.py
runesanalyzer/data_runes/RUNDATA.csv
runesanalyzer-1.0.5.dist-info/LICENSE
runesanalyzer-1.0.5.dist-info/METADATA
runesanalyzer-1.0.5.dist-info/WHEEL
runesanalyzer-1.0.5.dist-info/top_level.txt
runesanalyzer-1.0.5.dist-info/zip-safe
runesanalyzer-1.0.5.dist-info/RECORD
