Metadata-Version: 2.1
Name: runesanalyzer
Version: 1.0.5
Summary: Gathers different kinds of runic inscriptions
Home-page: https://github.com/clemsciences/runes-analyzer
Author: Clément Besnier
Author-email: clemsciences@gmail.com
License: License :: OSI Approved :: MIT License
Keywords: runes,corpus
Platform: UNKNOWN
Classifier: Programming Language :: Python :: 3
Classifier: Operating System :: OS Independent
Classifier: License :: OSI Approved :: MIT License
Classifier: Topic :: Text Processing
Requires-Python: >=3.6
